cuthon.py
cuthon-0.5.dist-info/METADATA
cuthon-0.5.dist-info/RECORD
cuthon-0.5.dist-info/WHEEL
cuthon-0.5.dist-info/entry_points.txt
cuthon-0.5.dist-info/top_level.txt
