Metadata-Version: 2.1
Name: cuthon
Version: 0.5
Summary: A simple tool to select the first available GPU(s) and run Python
Home-page: https://github.com/awni/cuthon
Author: Awni Hannun
Author-email: awni@stanford.edu
License: MIT
Keywords: gpu development cuda
Platform: UNKNOWN
Classifier: Intended Audience :: Developers
Classifier: License :: OSI Approved :: MIT License
Classifier: Programming Language :: Python :: 2.7
Classifier: Programming Language :: Python :: 3.4
Classifier: Programming Language :: Python :: 3.5
